mm0204/__init__.py
mm0204/data.py
mm0204-1.0.0.dist-info/METADATA
mm0204-1.0.0.dist-info/WHEEL
mm0204-1.0.0.dist-info/top_level.txt
mm0204-1.0.0.dist-info/RECORD
