Metadata-Version: 2.1
Name: mm0204
Version: 1.0.0
Summary: xD
Home-page: UNKNOWN
Author: qdzzzxc
License: UNKNOWN
Keywords: example python
Platform: UNKNOWN
Classifier: Programming Language :: Python :: 3.7
Classifier: License :: OSI Approved :: MIT License
Classifier: Operating System :: OS Independent
Requires-Python: >=3.7
Requires-Dist: pyperclip >=1.8.2
